lully/__init__.py
lully/collections.py
lully/confiseur.py
lully/fief.py
lully/itermore.py
lully/kotlin.py
lully/random.py
lully-0.0.4.dist-info/LICENCE
lully-0.0.4.dist-info/METADATA
lully-0.0.4.dist-info/WHEEL
lully-0.0.4.dist-info/top_level.txt
lully-0.0.4.dist-info/RECORD
