Metadata-Version: 2.1
Name: lully
Version: 0.0.4
Summary: Helpers for Python
Home-page: https://github.com/aluriak/lully
Author: Lucas Bourneuf
Author-email: lucas@bourneuf.net
License: GPLv3
Keywords: helpers,lib
Platform: UNKNOWN
Classifier: License :: OSI Approved :: GNU General Public License v3 (GPLv3)
Classifier: Development Status :: 4 - Beta
Classifier: Programming Language :: Python :: 3
Classifier: Programming Language :: Python :: 3.6
Classifier: Programming Language :: Python :: 3.7
Classifier: Programming Language :: Python :: 3.8
Classifier: Programming Language :: Python :: 3.9
License-File: LICENCE
